CHANGELOG.txt
LICENSE.txt
MANIFEST.in
README.txt
setup.py
nks_pm_functions.egg-info/PKG-INFO
nks_pm_functions.egg-info/SOURCES.txt
nks_pm_functions.egg-info/dependency_links.txt
nks_pm_functions.egg-info/top_level.txt
pm_functions/__init__.py
pm_functions/mysql_functions.py