Metadata-Version: 1.1
Name: nks-pm-functions
Version: 0.0.1
Summary: A short module only I will use
Home-page: UNKNOWN
Author: Nathaniel Kate Simon
Author-email: nathanielkatesimon@gmail.com
License: UNKNOWN
Keywords: Nothing
Platform: UNKNOWN
Classifier: Development Status :: 5 - Production/Stable
Classifier: Intended Audience :: Education
Classifier: Operating System :: Microsoft :: Windows :: Windows 10
Classifier: License :: OSI Approved :: MIT License
Classifier: Programming Language :: Python :: 3
